dispatchr/__init__.py
dispatchr/core.py
dispatchr/models.py
dispatchr/prompts.yaml
dispatchr/reg.py
dispatchr/sdk.py
dispatchr-0.1.4.dist-info/METADATA
dispatchr-0.1.4.dist-info/WHEEL
dispatchr-0.1.4.dist-info/entry_points.txt
dispatchr-0.1.4.dist-info/top_level.txt
dispatchr-0.1.4.dist-info/RECORD
